ti_pcg_lib/__init__.py
ti_pcg_lib/secret.py
ti_pcg_lib/utils.py
ti_pcg_lib-0.0.2.dist-info/METADATA
ti_pcg_lib-0.0.2.dist-info/WHEEL
ti_pcg_lib-0.0.2.dist-info/licenses/LICENSE
ti_pcg_lib-0.0.2.dist-info/RECORD
