Metadata-Version: 2.1
Name: ti_pcg_lib
Version: 0.0.2
Summary: A small GCP utility library
Project-URL: Homepage, http://github.com
Project-URL: Bug Tracker, http://github.com
Author-email: Tim Hespel <timothee.hespel@adeo.com>
License-File: LICENSE
Classifier: License :: OSI Approved :: MIT License
Classifier: Operating System :: OS Independent
Classifier: Programming Language :: Python :: 3
Requires-Python: >=3.7
Requires-Dist: google-cloud-secret-manager
